{
  "@context": "https://linked.art/ns/v1/linked-art.json",
  "id": "urn:nlux:f4bea5dfd36a522abaa3eeac63fca630",
  "type": "HumanMadeObject",
  "_label": "Stilleven met rozen in en vaas",
  "identified_by": [
    {
      "type": "Name",
      "content": "Stilleven met rozen in en vaas",
      "classified_as": [
        {
          "id": "http://vocab.getty.edu/aat/300404670",
          "_label": "preferred name"
        }
      ]
    },
    {
      "type": "Identifier",
      "content": "150",
      "classified_as": [
        {
          "id": "http://vocab.getty.edu/aat/300312355",
          "_label": "accession number"
        }
      ],
      "assigned_by": [
        {
          "type": "AttributeAssignment",
          "carried_out_by": [
            {
              "type": "Group",
              "_label": "Teylers Museum",
              "id": "https://teylers.adlibhosting.com/nlux/group/teylers-museum"
            }
          ]
        }
      ]
    }
  ],
  "subject_of": [
    {
      "type": "LinguisticObject",
      "digitally_carried_by": [
        {
          "type": "DigitalObject",
          "classified_as": [
            {
              "id": "http://vocab.getty.edu/aat/300264578",
              "_label": "web page"
            }
          ],
          "access_point": [
            {
              "id": "https://teylers.adlibhosting.com/ais6/search/Details/collect/150"
            }
          ],
          "format": "text/html",
          "identified_by": [
            {
              "type": "Name",
              "content": "Teylers Museum catalog page"
            }
          ]
        }
      ]
    }
  ],
  "_harvest": {
    "source_url": "https://teylers.adlibhosting.com/ais6/search/Details/collect/150",
    "local_id": "f4bea5dfd36a522abaa3eeac63fca630",
    "harvested_at": "2026-04-06T06:15:59.707105",
    "augmented": false
  },
  "referred_to_by": [
    {
      "type": "LinguisticObject",
      "content": "2023-12-08T14:00:30",
      "classified_as": [
        {
          "id": "http://vocab.getty.edu/aat/300411780",
          "_label": "@created"
        }
      ],
      "identified_by": [
        {
          "type": "Name",
          "content": "@created"
        }
      ]
    },
    {
      "type": "LinguisticObject",
      "content": "2024-10-01T11:19:02",
      "classified_as": [
        {
          "id": "http://vocab.getty.edu/aat/300411780",
          "_label": "@modification"
        }
      ],
      "identified_by": [
        {
          "type": "Name",
          "content": "@modification"
        }
      ]
    },
    {
      "type": "LinguisticObject",
      "content": "1966",
      "classified_as": [
        {
          "id": "http://vocab.getty.edu/aat/300411780",
          "_label": "Dating.dating.date.end"
        }
      ],
      "identified_by": [
        {
          "type": "Name",
          "content": "Dating.dating.date.end"
        }
      ]
    },
    {
      "type": "LinguisticObject",
      "content": "1966",
      "classified_as": [
        {
          "id": "http://vocab.getty.edu/aat/300411780",
          "_label": "Dating.dating.date.start"
        }
      ],
      "identified_by": [
        {
          "type": "Name",
          "content": "Dating.dating.date.start"
        }
      ]
    },
    {
      "type": "LinguisticObject",
      "content": "x",
      "classified_as": [
        {
          "id": "http://vocab.getty.edu/aat/300411780",
          "_label": "Media.media.reference.publish_on_web"
        }
      ],
      "identified_by": [
        {
          "type": "Name",
          "content": "Media.media.reference.publish_on_web"
        }
      ]
    },
    {
      "type": "LinguisticObject",
      "content": "KS 2000 006.jpg",
      "classified_as": [
        {
          "id": "http://vocab.getty.edu/aat/300411780",
          "_label": "Media.media.reference.reference_number"
        }
      ],
      "identified_by": [
        {
          "type": "Name",
          "content": "Media.media.reference.reference_number"
        }
      ]
    },
    {
      "type": "LinguisticObject",
      "content": "x",
      "classified_as": [
        {
          "id": "http://vocab.getty.edu/aat/300411780",
          "_label": "Media.media.reference.publish_on_web"
        }
      ],
      "identified_by": [
        {
          "type": "Name",
          "content": "Media.media.reference.publish_on_web"
        }
      ]
    },
    {
      "type": "LinguisticObject",
      "content": "KS 2000 006 verso.jpg",
      "classified_as": [
        {
          "id": "http://vocab.getty.edu/aat/300411780",
          "_label": "Media.media.reference.reference_number"
        }
      ],
      "identified_by": [
        {
          "type": "Name",
          "content": "Media.media.reference.reference_number"
        }
      ]
    },
    {
      "type": "LinguisticObject",
      "content": "schilderij",
      "classified_as": [
        {
          "id": "http://vocab.getty.edu/aat/300411780",
          "_label": "Object_name.object_name"
        }
      ],
      "identified_by": [
        {
          "type": "Name",
          "content": "Object_name.object_name"
        }
      ]
    },
    {
      "type": "LinguisticObject",
      "content": "Rueter, Georg (1875-1966)",
      "classified_as": [
        {
          "id": "http://vocab.getty.edu/aat/300411780",
          "_label": "Production.creator"
        }
      ],
      "identified_by": [
        {
          "type": "Name",
          "content": "Production.creator"
        }
      ]
    },
    {
      "type": "LinguisticObject",
      "content": "schilder",
      "classified_as": [
        {
          "id": "http://vocab.getty.edu/aat/300411780",
          "_label": "Production.creator.role"
        }
      ],
      "identified_by": [
        {
          "type": "Name",
          "content": "Production.creator.role"
        }
      ]
    },
    {
      "type": "LinguisticObject",
      "content": "Stilleven met rozen in en vaas",
      "classified_as": [
        {
          "id": "http://vocab.getty.edu/aat/300411780",
          "_label": "Title.title"
        }
      ],
      "identified_by": [
        {
          "type": "Name",
          "content": "Title.title"
        }
      ]
    },
    {
      "type": "LinguisticObject",
      "content": "KS 2000 006",
      "classified_as": [
        {
          "id": "http://vocab.getty.edu/aat/300411780",
          "_label": "object_number"
        }
      ],
      "identified_by": [
        {
          "type": "Name",
          "content": "object_number"
        }
      ]
    }
  ]
}