{
  "@context": "https://linked.art/ns/v1/linked-art.json",
  "id": "urn:nlux:ea1ab8040375a2608a89d11708ec1ff0",
  "type": "HumanMadeObject",
  "_label": "Gezicht op de Sint Antoniespoort te Amsterdam vanaf het zuiden gezien",
  "identified_by": [
    {
      "type": "Name",
      "content": "Gezicht op de Sint Antoniespoort te Amsterdam vanaf het zuiden gezien",
      "classified_as": [
        {
          "id": "http://vocab.getty.edu/aat/300404670",
          "_label": "preferred name"
        }
      ]
    },
    {
      "type": "Identifier",
      "content": "28",
      "classified_as": [
        {
          "id": "http://vocab.getty.edu/aat/300312355",
          "_label": "accession number"
        }
      ],
      "assigned_by": [
        {
          "type": "AttributeAssignment",
          "carried_out_by": [
            {
              "type": "Group",
              "_label": "Teylers Museum",
              "id": "https://teylers.adlibhosting.com/nlux/group/teylers-museum"
            }
          ]
        }
      ]
    }
  ],
  "subject_of": [
    {
      "type": "LinguisticObject",
      "digitally_carried_by": [
        {
          "type": "DigitalObject",
          "classified_as": [
            {
              "id": "http://vocab.getty.edu/aat/300264578",
              "_label": "web page"
            }
          ],
          "access_point": [
            {
              "id": "https://teylers.adlibhosting.com/ais6/search/Details/collect/28"
            }
          ],
          "format": "text/html",
          "identified_by": [
            {
              "type": "Name",
              "content": "Teylers Museum catalog page"
            }
          ]
        }
      ]
    }
  ],
  "_harvest": {
    "source_url": "https://teylers.adlibhosting.com/ais6/search/Details/collect/28",
    "local_id": "ea1ab8040375a2608a89d11708ec1ff0",
    "harvested_at": "2026-04-06T06:15:46.981030",
    "augmented": false
  },
  "referred_to_by": [
    {
      "type": "LinguisticObject",
      "content": "2023-12-08T13:59:43",
      "classified_as": [
        {
          "id": "http://vocab.getty.edu/aat/300411780",
          "_label": "@created"
        }
      ],
      "identified_by": [
        {
          "type": "Name",
          "content": "@created"
        }
      ]
    },
    {
      "type": "LinguisticObject",
      "content": "2025-03-14T16:40:17",
      "classified_as": [
        {
          "id": "http://vocab.getty.edu/aat/300411780",
          "_label": "@modification"
        }
      ],
      "identified_by": [
        {
          "type": "Name",
          "content": "@modification"
        }
      ]
    },
    {
      "type": "LinguisticObject",
      "content": "1670",
      "classified_as": [
        {
          "id": "http://vocab.getty.edu/aat/300411780",
          "_label": "Dating.dating.date.end"
        }
      ],
      "identified_by": [
        {
          "type": "Name",
          "content": "Dating.dating.date.end"
        }
      ]
    },
    {
      "type": "LinguisticObject",
      "content": "voor",
      "classified_as": [
        {
          "id": "http://vocab.getty.edu/aat/300411780",
          "_label": "Dating.dating.date.end.prec"
        }
      ],
      "identified_by": [
        {
          "type": "Name",
          "content": "Dating.dating.date.end.prec"
        }
      ]
    },
    {
      "type": "LinguisticObject",
      "content": "x",
      "classified_as": [
        {
          "id": "http://vocab.getty.edu/aat/300411780",
          "_label": "Media.media.reference.publish_on_web"
        }
      ],
      "identified_by": [
        {
          "type": "Name",
          "content": "Media.media.reference.publish_on_web"
        }
      ]
    },
    {
      "type": "LinguisticObject",
      "content": "R+ 001.jpg",
      "classified_as": [
        {
          "id": "http://vocab.getty.edu/aat/300411780",
          "_label": "Media.media.reference.reference_number"
        }
      ],
      "identified_by": [
        {
          "type": "Name",
          "content": "Media.media.reference.reference_number"
        }
      ]
    },
    {
      "type": "LinguisticObject",
      "content": "tekening",
      "classified_as": [
        {
          "id": "http://vocab.getty.edu/aat/300411780",
          "_label": "Object_name.object_name"
        }
      ],
      "identified_by": [
        {
          "type": "Name",
          "content": "Object_name.object_name"
        }
      ]
    },
    {
      "type": "LinguisticObject",
      "content": "Heyden, Jan van der (1637-1712)",
      "classified_as": [
        {
          "id": "http://vocab.getty.edu/aat/300411780",
          "_label": "Production.creator"
        }
      ],
      "identified_by": [
        {
          "type": "Name",
          "content": "Production.creator"
        }
      ]
    },
    {
      "type": "LinguisticObject",
      "content": "tekenaar",
      "classified_as": [
        {
          "id": "http://vocab.getty.edu/aat/300411780",
          "_label": "Production.creator.role"
        }
      ],
      "identified_by": [
        {
          "type": "Name",
          "content": "Production.creator.role"
        }
      ]
    },
    {
      "type": "LinguisticObject",
      "content": "Gezicht op de Sint Antoniespoort te Amsterdam vanaf het zuiden gezien",
      "classified_as": [
        {
          "id": "http://vocab.getty.edu/aat/300411780",
          "_label": "Title.title"
        }
      ],
      "identified_by": [
        {
          "type": "Name",
          "content": "Title.title"
        }
      ]
    },
    {
      "type": "LinguisticObject",
      "content": "R+ 001",
      "classified_as": [
        {
          "id": "http://vocab.getty.edu/aat/300411780",
          "_label": "object_number"
        }
      ],
      "identified_by": [
        {
          "type": "Name",
          "content": "object_number"
        }
      ]
    }
  ]
}